README
setup.py
daisydukes/__init__.py
daisydukes/archive.py
daisydukes/package.py
daisydukes/upload.py
daisydukes/util.py
daisydukes.egg-info/PKG-INFO
daisydukes.egg-info/SOURCES.txt
daisydukes.egg-info/dependency_links.txt
daisydukes.egg-info/entry_points.txt
daisydukes.egg-info/not-zip-safe
daisydukes.egg-info/top_level.txt