Metadata-Version: 1.1
Name: daisydukes
Version: 0.0.1
Summary: Set up a minimal, yet comfortable structure         for a Python project
Home-page: https://github.com/rossdylan/daisydukes
Author: Ross Delinger
Author-email: ross.delinger@gmail.com
License: GPLv3+
Keywords: python development project packaging,deployment
Platform: UNKNOWN
Classifier: Development Status :: 2 - Pre-Alpha
Classifier: Intended Audience :: Developers
Classifier: License :: OSI Approved :: GNU General Public License (GPL)
Classifier: Programming Language :: Python :: 2
Classifier: Topic :: Software Development
Classifier: Topic :: Utilities
